tsl2591/__init__.py
tsl2591/tsl2591.py
tsl2591-0.0.3.dist-info/LICENSE
tsl2591-0.0.3.dist-info/METADATA
tsl2591-0.0.3.dist-info/WHEEL
tsl2591-0.0.3.dist-info/top_level.txt
tsl2591-0.0.3.dist-info/RECORD
