Metadata-Version: 2.1
Name: tsl2591
Version: 0.0.3
Summary: tsl2591 python driver for stickytoe framework
Home-page: https://github.com/ryanchaiyakul/sht3x
Author: Ryan Chaiyakul
License: UNKNOWN
Platform: UNKNOWN
Classifier: Programming Language :: Python :: 3
Classifier: License :: OSI Approved :: MIT License
Classifier: Operating System :: OS Independent
Requires-Python: >=3.6
Requires-Dist: Adafruit-Blinka (==3.0.0)
Requires-Dist: adafruit-circuitpython-busdevice (==4.0.0)
Requires-Dist: adafruit-circuitpython-tsl2591 (==1.1.3)
Requires-Dist: Adafruit-PlatformDetect (==1.3.4)
Requires-Dist: Adafruit-PureIO (==0.2.3)
Requires-Dist: stickytoe-device (>=0.0.2)
